easysrv/__init__.py
easysrv/core/__init__.py
easysrv/core/srv.py
easysrv/utils/__init__.py
easysrv/utils/mlutils.py
easysrv-0.0.3.dist-info/LICENSE
easysrv-0.0.3.dist-info/METADATA
easysrv-0.0.3.dist-info/WHEEL
easysrv-0.0.3.dist-info/top_level.txt
easysrv-0.0.3.dist-info/RECORD
