Metadata-Version: 2.1
Name: easysrv
Version: 0.0.3
Summary: Easy to use State Reversible Vampnet with fit, transform and fittransform methods
Home-page: https://github.com/DanielWicz/easysrv
Author: Daniel Wiczew
Author-email: daniel.wiczew@gmail.com
License: UNKNOWN
Project-URL: Documentation, https://github.com/DanielWicz/easysrv
Project-URL: Bug Reports, https://github.com/DanielWicz/easysrv/issues
Project-URL: Source Code, https://github.com/DanielWicz/easysrv
Keywords: machine learning,molecular dynamics,tensorflow
Platform: UNKNOWN
Classifier: Development Status :: 3 - Alpha
Classifier: Intended Audience :: Science/Research
Classifier: Topic :: Scientific/Engineering :: Artificial Intelligence
Classifier: Programming Language :: Python :: 3
Classifier: Programming Language :: Python :: 3.6
Classifier: Programming Language :: Python :: 3.7
Classifier: Programming Language :: Python :: 3.8
Classifier: Programming Language :: Python :: 3.9
Classifier: Programming Language :: Python :: 3 :: Only
Classifier: License :: OSI Approved :: MIT License
Classifier: Operating System :: OS Independent
Requires-Python: >=3.6
License-File: LICENSE
Requires-Dist: numpy
Requires-Dist: tensorflow
Requires-Dist: scipy
Provides-Extra: dev
Requires-Dist: check-manifest ; extra == 'dev'
